app/__init__.py
app/console.py
app/constants.py
app/enums.py
app/main.py
app/ops/__init__.py
app/ops/audit.py
app/ops/azenta.py
app/ops/box.py
app/ops/database.py
app/ops/database_user.py
app/ops/location.py
app/ops/lots.py
app/ops/order.py
app/ops/parts.py
app/ops/users.py
app/ops/variant.py
app/utils/__init__.py
app/utils/checks.py
app/utils/config.py
app/utils/datetime_utils.py
app/utils/part_util.py
app/utils/response_utils.py
app/utils/string_utils.py
app/utils/version_upgrade_check.py
sequins_inventory_tool-1.1.1.dist-info/licenses/LICENSE
sequins_inventory_tool-1.1.1.dist-info/METADATA
sequins_inventory_tool-1.1.1.dist-info/WHEEL
sequins_inventory_tool-1.1.1.dist-info/entry_points.txt
sequins_inventory_tool-1.1.1.dist-info/top_level.txt
sequins_inventory_tool-1.1.1.dist-info/RECORD
