Metadata-Version: 2.4
Name: sequins-inventory-tool
Version: 1.1.1
Summary: A tool for sequins inventory.
Author: The Sequins Software Team
License-Expression: Apache-2.0
Classifier: Development Status :: 3 - Alpha
Classifier: Programming Language :: Python
Requires-Python: >=3.13
License-File: LICENSE
Requires-Dist: cryptography==46.0.3
Requires-Dist: python-dotenv==1.2.1
Requires-Dist: pydantic==2.12.3
Requires-Dist: pymongo==4.15.3
Requires-Dist: requests==2.32.5
Requires-Dist: rich==14.2.0
Requires-Dist: packaging==25.0
Requires-Dist: pandas==2.3.3
Requires-Dist: platformdirs==4.5.0
Requires-Dist: tomlkit==0.13.3
Requires-Dist: typer==0.20.0
Requires-Dist: python-dateutil==2.9.0.post0
Provides-Extra: test
Requires-Dist: mongomock==4.3.0; extra == "test"
Requires-Dist: pytest==8.4.2; extra == "test"
Requires-Dist: pytest-asyncio==1.2.0; extra == "test"
Requires-Dist: pytest-cov==7.0.0; extra == "test"
Requires-Dist: pytest-env==1.2.0; extra == "test"
Requires-Dist: pytest-mock==3.15.1; extra == "test"
Requires-Dist: pytest-mongodb==2.4.0; extra == "test"
Requires-Dist: requests-mock==1.12.1; extra == "test"
Requires-Dist: responses==0.25.8; extra == "test"
Dynamic: license-file
